odoo/addons/purchase_no_rfq/README.rst
odoo/addons/purchase_no_rfq/__init__.py
odoo/addons/purchase_no_rfq/__manifest__.py
odoo/addons/purchase_no_rfq/hooks.py
odoo/addons/purchase_no_rfq/i18n/fr.po
odoo/addons/purchase_no_rfq/i18n/purchase_no_rfq.pot
odoo/addons/purchase_no_rfq/models/__init__.py
odoo/addons/purchase_no_rfq/models/purchase_order.py
odoo/addons/purchase_no_rfq/readme/CONTRIBUTORS.rst
odoo/addons/purchase_no_rfq/readme/DESCRIPTION.rst
odoo/addons/purchase_no_rfq/readme/ROADMAP.rst
odoo/addons/purchase_no_rfq/reports/ir_actions_report.xml
odoo/addons/purchase_no_rfq/reports/purchase_order_template.xml
odoo/addons/purchase_no_rfq/static/description/icon.png
odoo/addons/purchase_no_rfq/static/description/index.html
odoo/addons/purchase_no_rfq/static/description/purchase_order_form.png
odoo/addons/purchase_no_rfq/static/description/purchase_order_tree.png
odoo/addons/purchase_no_rfq/views/view_purchase_order.xml
odoo12_addon_purchase_no_rfq-12.0.1.0.0.99.dev4.dist-info/METADATA
odoo12_addon_purchase_no_rfq-12.0.1.0.0.99.dev4.dist-info/WHEEL
odoo12_addon_purchase_no_rfq-12.0.1.0.0.99.dev4.dist-info/top_level.txt
odoo12_addon_purchase_no_rfq-12.0.1.0.0.99.dev4.dist-info/RECORD
